vantiqsdk.py
vantiqsdk-1.4.6.dist-info/licenses/LICENSE.txt
vantiqsdk-1.4.6.dist-info/METADATA
vantiqsdk-1.4.6.dist-info/WHEEL
vantiqsdk-1.4.6.dist-info/top_level.txt
vantiqsdk-1.4.6.dist-info/RECORD
