Metadata-Version: 2.4
Name: vantiqsdk
Version: 1.4.6
Summary: SDK for working with the Vantiq system
Author-email: Vantiq <fcarter@vantiq.com>
License: MIT
Project-URL: Homepage, https://github.com/vantiq/vantiq-python-sdk
Classifier: Development Status :: 5 - Production/Stable
Classifier: License :: OSI Approved :: MIT License
Classifier: Programming Language :: Python :: 3.10
Classifier: Programming Language :: Python :: 3.11
Classifier: Programming Language :: Python :: 3.12
Requires-Python: >=3.10
License-File: LICENSE.txt
Requires-Dist: websockets
Requires-Dist: requests>=2.32.3
Requires-Dist: urllib3>=2.5.0
Requires-Dist: aiohttp>=3.12.14
Dynamic: license-file
